<ProcessingProcedure>

    <ProcessingCommand>
        <Command xmlns="">hsd_importdata</Command>
        <ParameterSet>
        </ParameterSet>
    </ProcessingCommand>

    <ProcessingCommand>
        <Command xmlns="">hsd_inspectdata</Command>
        <ParameterSet>
        </ParameterSet>
    </ProcessingCommand>

    <ProcessingCommand>
        <Command xmlns="">hsd_caltsys</Command>
        <ParameterSet>
        </ParameterSet>
    </ProcessingCommand>

    <ProcessingCommand>
        <Command xmlns="">hsd_calsky</Command>
        <ParameterSet>
        </ParameterSet>
    </ProcessingCommand>

    <ProcessingCommand>
        <Command xmlns="">hsd_applycal</Command>
        <ParameterSet>
        </ParameterSet>
    </ProcessingCommand>

    <ProcessingCommand>
        <Command xmlns="">hsd_baseline</Command>
        <ParameterSet>
        </ParameterSet>
    </ProcessingCommand>

    <ProcessingCommand>
        <Command xmlns="">hsd_flagdata</Command>
        <ParameterSet>
        </ParameterSet>
    </ProcessingCommand>

    <ProcessingCommand>
        <Command xmlns="">hsd_imaging</Command>
        <ParameterSet>
        </ParameterSet>
    </ProcessingCommand>

    <ProcessingCommand>
        <Command xmlns="">hsd_baseline</Command>
        <ParameterSet>
        </ParameterSet>
    </ProcessingCommand>

    <ProcessingCommand>
        <Command xmlns="">hsd_flagdata</Command>
        <ParameterSet>
        </ParameterSet>
    </ProcessingCommand>

    <ProcessingCommand>
        <Command xmlns="">hsd_imaging</Command>
        <ParameterSet>
        </ParameterSet>
    </ProcessingCommand>

    <ProcessingCommand>
        <Command xmlns="">hsd_exportdata</Command>
        <ParameterSet>
        </ParameterSet>
    </ProcessingCommand>

</ProcessingProcedure>
